dbotu/__init__.py
dbotu-1.5.3.data/scripts/dbotu3.py
dbotu-1.5.3.data/scripts/dbotu_rep_seqs.py
dbotu-1.5.3.data/scripts/dbotu_restart.py
dbotu-1.5.3.dist-info/METADATA
dbotu-1.5.3.dist-info/WHEEL
dbotu-1.5.3.dist-info/top_level.txt
dbotu-1.5.3.dist-info/RECORD
