Metadata-Version: 2.1
Name: dbotu
Version: 1.5.3
Summary: Distribution-based OTU calling
Home-page: http://github.com/swo/dbotu3
Author: Scott Olesen
Author-email: swo@alum.mit.edu
License: License :: OSI Approved :: MIT License
Platform: any
Classifier: Development Status :: 4 - Beta
Classifier: Environment :: Console
Classifier: Programming Language :: Python :: 2.7
Classifier: Programming Language :: Python :: 3.6
Classifier: Topic :: Scientific/Engineering :: Bio-Informatics
Requires-Dist: numpy
Requires-Dist: pandas
Requires-Dist: scipy
Requires-Dist: biopython
Requires-Dist: python-Levenshtein
